astronomy/__init__.py
astronomy-0.0.1.dist-info/METADATA
astronomy-0.0.1.dist-info/RECORD
astronomy-0.0.1.dist-info/WHEEL
astronomy-0.0.1.dist-info/top_level.txt
