Metadata-Version: 2.1
Name: astronomy
Version: 0.0.1
Summary: Astronomy!
Home-page: https://github.com/rodluger/astronomy
Author: Rodrigo Luger
Author-email: rodluger@gmail.com
License: MIT
Platform: UNKNOWN
